ltiauthenticator/__init__.py
ltiauthenticator/_version.py
ltiauthenticator/utils.py
ltiauthenticator/lti11/__init__.py
ltiauthenticator/lti11/auth.py
ltiauthenticator/lti11/constants.py
ltiauthenticator/lti11/handlers.py
ltiauthenticator/lti11/templates.py
ltiauthenticator/lti11/validator.py
ltiauthenticator/lti13/__init__.py
ltiauthenticator/lti13/auth.py
ltiauthenticator/lti13/constants.py
ltiauthenticator/lti13/error.py
ltiauthenticator/lti13/handlers.py
ltiauthenticator/lti13/validator.py
jupyterhub_ltiauthenticator-1.6.2.dist-info/METADATA
jupyterhub_ltiauthenticator-1.6.2.dist-info/WHEEL
jupyterhub_ltiauthenticator-1.6.2.dist-info/licenses/LICENSE
jupyterhub_ltiauthenticator-1.6.2.dist-info/RECORD
