Metadata-Version: 2.1
Name: jupyterhub-ltiauthenticator
Version: 1.6.2
Summary: JupyterHub authenticator implementing LTI v1.1 and LTI v1.3
Project-URL: Documentation, https://ltiauthenticator.readthedocs.io
Project-URL: Source, https://github.com/jupyterhub/ltiauthenticator
Project-URL: Issues, https://github.com/jupyterhub/ltiauthenticator/issues
Author-email: Yuvi Panda <yuvipanda@gmail.com>, Jupyter Contributors <jupyter@googlegroups.com>
License: BSD 3-Clause License
License-File: LICENSE
Keywords: authenticator,jupyterhub
Classifier: Development Status :: 5 - Production/Stable
Classifier: Programming Language :: Python :: 3
Requires-Python: >=3.8
Requires-Dist: escapism>=1.0.1
Requires-Dist: jupyterhub>=1.2
Requires-Dist: oauthlib>=3.2.2
Requires-Dist: pyjwt[crypto]>=2.7.0
Requires-Dist: traitlets>=5.1.0
Provides-Extra: dev
Requires-Dist: pre-commit; extra == 'dev'
Provides-Extra: test
Requires-Dist: pytest; extra == 'test'
Requires-Dist: pytest-asyncio; extra == 'test'
Requires-Dist: pytest-cov; extra == 'test'
